zaban/__init__.py
zaban/_client.py
zaban/_exceptions.py
zaban/_utils.py
zaban/client.py
zaban/py.typed
zaban/version.py
zaban/resources/__init__.py
zaban/resources/audio.py
zaban/resources/translation.py
zaban/resources/transliteration.py
zaban/types/__init__.py
zaban/types/common.py
zaban/types/stt.py
zaban/types/translation.py
zaban/types/transliteration.py
zaban/types/tts.py
zaban-0.1.3.dist-info/licenses/LICENSE
zaban-0.1.3.dist-info/METADATA
zaban-0.1.3.dist-info/WHEEL
zaban-0.1.3.dist-info/top_level.txt
zaban-0.1.3.dist-info/RECORD
