Metadata-Version: 2.4
Name: zaban
Version: 0.1.3
Summary: Official Python client for Zaban API - Zaban services for Indian languages
Author-email: Zaban Team <prajjwalkumarpanzade01@gmail.com>
License: MIT
Project-URL: Homepage, https://github.com/prajjwalkumarpanzade/zaban-client
Project-URL: Documentation, https://github.com/prajjwalkumarpanzade/zaban-client/blob/main/README.md
Project-URL: Repository, https://github.com/prajjwalkumarpanzade/zaban-client
Project-URL: Bug Tracker, https://github.com/prajjwalkumarpanzade/zaban-client/issues
Keywords: zaban,translation,indictrans2,tts,text-to-speech,stt,speech-to-text,transliteration,indian-languages,hindi,bengali,tamil,telugu,nlp,machine-translation
Classifier: Development Status :: 4 - Beta
Classifier: Intended Audience :: Developers
Classifier: License :: OSI Approved :: MIT License
Classifier: Operating System :: OS Independent
Classifier: Programming Language :: Python :: 3
Classifier: Programming Language :: Python :: 3.8
Classifier: Programming Language :: Python :: 3.9
Classifier: Programming Language :: Python :: 3.10
Classifier: Programming Language :: Python :: 3.11
Classifier: Programming Language :: Python :: 3.12
Classifier: Topic :: Software Development :: Libraries :: Python Modules
Classifier: Topic :: Text Processing :: Linguistic
Classifier: Topic :: Scientific/Engineering :: Artificial Intelligence
Requires-Python: >=3.8
License-File: LICENSE
Requires-Dist: httpx>=0.27.0
Requires-Dist: pydantic>=2.0.0
Requires-Dist: typing-extensions>=4.7.0
Provides-Extra: dev
Requires-Dist: pytest>=7.0.0; extra == "dev"
Requires-Dist: pytest-asyncio>=0.21.0; extra == "dev"
Requires-Dist: black>=23.0.0; extra == "dev"
Requires-Dist: mypy>=1.0.0; extra == "dev"
Requires-Dist: ruff>=0.1.0; extra == "dev"
Requires-Dist: build>=1.0.0; extra == "dev"
Requires-Dist: twine>=4.0.0; extra == "dev"
Dynamic: license-file
